LICENSE
MANIFEST.in
README.md
setup.py
pwuvzifqnb/__init__.py
pwuvzifqnb/api_helper.py
pwuvzifqnb/configuration.py
pwuvzifqnb/decorators.py
pwuvzifqnb/pwuvzifqnb_client.py
pwuvzifqnb.egg-info/PKG-INFO
pwuvzifqnb.egg-info/SOURCES.txt
pwuvzifqnb.egg-info/dependency_links.txt
pwuvzifqnb.egg-info/requires.txt
pwuvzifqnb.egg-info/top_level.txt
pwuvzifqnb/controllers/__init__.py
pwuvzifqnb/controllers/api_controller.py
pwuvzifqnb/controllers/base_controller.py
pwuvzifqnb/exceptions/__init__.py
pwuvzifqnb/exceptions/api_exception.py
pwuvzifqnb/http/__init__.py
pwuvzifqnb/http/http_call_back.py
pwuvzifqnb/http/http_client.py
pwuvzifqnb/http/http_context.py
pwuvzifqnb/http/http_method_enum.py
pwuvzifqnb/http/http_request.py
pwuvzifqnb/http/http_response.py
pwuvzifqnb/http/requests_client.py
pwuvzifqnb/http/auth/__init__.py
pwuvzifqnb/http/auth/basic_auth.py
pwuvzifqnb/models/__init__.py
pwuvzifqnb/models/suite_code_enum.py
tests/__init__.py
tests/http_response_catcher.py
tests/test_helper.py
tests/controllers/__init__.py
tests/controllers/controller_test_base.py
tests/controllers/test_api_controller.py